Workbook

Sheet Raw Data
A1: order_id | B1: date | C1: region | D1: category | E1: channel | F1: units | G1: unit_price | H1: revenue | I1: cost | J1: profit | K1: month
A2: 5001 | B2: 45566 | C2: West | D2: Home & Kitchen | E2: Online | F2: 3 | G2: 62.9 | H2: 188.69 | I2: 116.73 | J2: =H2-I2 -> 71.96 | K2: =TEXT(B2,"mmm-yy") -> Oct-24
A3: 5002 | B3: 45566 | C3: West | D3: Apparel | E3: Online | F3: 4 | G3: 44.76 | H3: 179.03 | I3: 105.17 | J3: =H3-I3 -> 73.86 | K3: =TEXT(B3,"mmm-yy") -> Oct-24
A4: 5003 | B4: 45566 | C4: West | D4: Electronics | E4: Online | F4: 1 | G4: 199.09 | H4: 199.09 | I4: 116.1 | J4: =H4-I4 -> 82.99 | K4: =TEXT(B4,"mmm-yy") -> Oct-24
A5: 5004 | B5: 45566 | C5: West | D5: Electronics | E5: In-Store | F5: 3 | G5: 161.93 | H5: 485.79 | I5: 275.59 | J5: =H5-I5 -> 210.2 | K5: =TEXT(B5,"mmm-yy") -> Oct-24
A6: 5005 | B6: 45566 | C6: East | D6: Beauty | E6: In-Store | F6: 1 | G6: 27.86 | H6: 29.26 | I6: 18.43 | J6: =H6-I6 -> 10.83 | K6: =TEXT(B6,"mmm-yy") -> Oct-24
A7: 5006 | B7: 45566 | C7: West | D7: Apparel | E7: Online | F7: 1 | G7: 39.9 | H7: 39.9 | I7: 25.93 | J7: =H7-I7 -> 13.97 | K7: =TEXT(B7,"mmm-yy") -> Oct-24
A8: 5007 | B8: 45566 | C8: South | D8: Home & Kitchen | E8: Online | F8: 4 | G8: 50.33 | H8: 151 | I8: 88.6 | J8: =H8-I8 -> 62.4 | K8: =TEXT(B8,"mmm-yy") -> Oct-24
A9: 5008 | B9: 45566 | C9: West | D9: Apparel | E9: Online | F9: 2 | G9: 47.53 | H9: 95.05 | I9: 63.48 | J9: =H9-I9 -> 31.57 | K9: =TEXT(B9,"mmm-yy") -> Oct-24
A10: 5009 | B10: 45566 | C10: North | D10: Beauty | E10: Online | F10: 3 | G10: 33.07 | H10: 114.07 | I10: 66.58 | J10: =H10-I10 -> 47.49 | K10: =TEXT(B10,"mmm-yy") -> Oct-24
A11: 5010 | B11: 45566 | C11: South | D11: Home & Kitchen | E11: Online | F11: 2 | G11: 74.23 | H11: 111.35 | I11: 68.83 | J11: =H11-I11 -> 42.52 | K11: =TEXT(B11,"mmm-yy") -> Oct-24
A12: 5011 | B12: 45566 | C12: East | D12: Sports | E12: In-Store | F12: 4 | G12: 57.77 | H12: 242.65 | I12: 151.04 | J12: =H12-I12 -> 91.61 | K12: =TEXT(B12,"mmm-yy") -> Oct-24
A13: 5012 | B13: 45566 | C13: West | D13: Electronics | E13: Online | F13: 2 | G13: 158.92 | H13: 317.83 | I13: 194.32 | J13: =H13-I13 -> 123.51 | K13: =TEXT(B13,"mmm-yy") -> Oct-24
... A5213: 10212 | B5213: 45930 | C5213: North | D5213: Beauty | E5213: Online | F5213: 4 | G5213: 27.08 | H5213: 124.55 | I5213: 71.44 | J5213: =H5213-I5213 -> 53.11 | K5213: =TEXT(B5213,"mmm-yy") -> Sep-25

Sheet Summary
A1: Retail Sales Performance — Summary
A3: Revenue & Margin by Region
A4: Region | B4: Revenue | C4: Cost | D4: Profit | E4: Margin %
A5: North | B5: =SUMIF('Raw Data'!C:C,A5,'Raw Data'!H:H) -> 346748.36 | C5: =SUMIF('Raw Data'!C:C,A5,'Raw Data'!I:I) -> 213192.98 | D5: =B5-C5 -> 133555.38 | E5: =IFERROR(D5/B5,0) -> 0.38516514
A6: South | B6: =SUMIF('Raw Data'!C:C,A6,'Raw Data'!H:H) -> 165000.62 | C6: =SUMIF('Raw Data'!C:C,A6,'Raw Data'!I:I) -> 101245.04 | D6: =B6-C6 -> 63755.58 | E6: =IFERROR(D6/B6,0) -> 0.386396
A7: East | B7: =SUMIF('Raw Data'!C:C,A7,'Raw Data'!H:H) -> 299479.9 | C7: =SUMIF('Raw Data'!C:C,A7,'Raw Data'!I:I) -> 184268.81 | D7: =B7-C7 -> 115211.09 | E7: =IFERROR(D7/B7,0) -> 0.38470392
A8: West | B8: =SUMIF('Raw Data'!C:C,A8,'Raw Data'!H:H) -> 270575.54 | C8: =SUMIF('Raw Data'!C:C,A8,'Raw Data'!I:I) -> 166708.42 | D8: =B8-C8 -> 103867.12 | E8: =IFERROR(D8/B8,0) -> 0.38387476
A11: Revenue by Category
A12: Category | B12: Revenue | C12: Units Sold
A13: Electronics | B13: =SUMIF('Raw Data'!D:D,A13,'Raw Data'!H:H) -> 623890.76 | C13: =SUMIF('Raw Data'!D:D,A13,'Raw Data'!F:F) -> 3441
A14: Apparel | B14: =SUMIF('Raw Data'!D:D,A14,'Raw Data'!H:H) -> 127492.89 | C14: =SUMIF('Raw Data'!D:D,A14,'Raw Data'!F:F) -> 2819
A15: Home & Kitchen | B15: =SUMIF('Raw Data'!D:D,A15,'Raw Data'!H:H) -> 156985.51 | C15: =SUMIF('Raw Data'!D:D,A15,'Raw Data'!F:F) -> 2392
A16: Beauty | B16: =SUMIF('Raw Data'!D:D,A16,'Raw Data'!H:H) -> 69844.4 | C16: =SUMIF('Raw Data'!D:D,A16,'Raw Data'!F:F) -> 2471
A17: Sports | B17: =SUMIF('Raw Data'!D:D,A17,'Raw Data'!H:H) -> 103590.86 | C17: =SUMIF('Raw Data'!D:D,A17,'Raw Data'!F:F) -> 1879
A19: Revenue by Channel
A20: Channel | B20: Revenue | C20: Orders
A21: Online | B21: =SUMIF('Raw Data'!E:E,A21,'Raw Data'!H:H) -> 551745.56 | C21: =COUNTIF('Raw Data'!E:E,A21) -> 2657
A22: In-Store | B22: =SUMIF('Raw Data'!E:E,A22,'Raw Data'!H:H) -> 340103.2 | C22: =COUNTIF('Raw Data'!E:E,A22) -> 1616
A23: Mobile App | B23: =SUMIF('Raw Data'!E:E,A23,'Raw Data'!H:H) -> 189955.66 | C23: =COUNTIF('Raw Data'!E:E,A23) -> 939

Sheet Monthly Trend
A1: Monthly Revenue Trend
A3: Month | B3: Revenue | C3: Profit
A4: Oct-24 | B4: =SUMIF('Raw Data'!K:K,A4,'Raw Data'!H:H) -> 85844.51 | C4: =SUMIF('Raw Data'!K:K,A4,'Raw Data'!J:J) -> 33068.92
A5: Nov-24 | B5: =SUMIF('Raw Data'!K:K,A5,'Raw Data'!H:H) -> 138612.75 | C5: =SUMIF('Raw Data'!K:K,A5,'Raw Data'!J:J) -> 53445.06
A6: Dec-24 | B6: =SUMIF('Raw Data'!K:K,A6,'Raw Data'!H:H) -> 136194.98 | C6: =SUMIF('Raw Data'!K:K,A6,'Raw Data'!J:J) -> 51939.77
A7: Jan-25 | B7: =SUMIF('Raw Data'!K:K,A7,'Raw Data'!H:H) -> 69115 | C7: =SUMIF('Raw Data'!K:K,A7,'Raw Data'!J:J) -> 26236.3
A8: Feb-25 | B8: =SUMIF('Raw Data'!K:K,A8,'Raw Data'!H:H) -> 75328.14 | C8: =SUMIF('Raw Data'!K:K,A8,'Raw Data'!J:J) -> 28922.19
A9: Mar-25 | B9: =SUMIF('Raw Data'!K:K,A9,'Raw Data'!H:H) -> 80833.96 | C9: =SUMIF('Raw Data'!K:K,A9,'Raw Data'!J:J) -> 31208.07
A10: Apr-25 | B10: =SUMIF('Raw Data'!K:K,A10,'Raw Data'!H:H) -> 85864.15 | C10: =SUMIF('Raw Data'!K:K,A10,'Raw Data'!J:J) -> 32736.91
A11: May-25 | B11: =SUMIF('Raw Data'!K:K,A11,'Raw Data'!H:H) -> 94403.89 | C11: =SUMIF('Raw Data'!K:K,A11,'Raw Data'!J:J) -> 36210.82
A12: Jun-25 | B12: =SUMIF('Raw Data'!K:K,A12,'Raw Data'!H:H) -> 69302.24 | C12: =SUMIF('Raw Data'!K:K,A12,'Raw Data'!J:J) -> 26733.99
A13: Jul-25 | B13: =SUMIF('Raw Data'!K:K,A13,'Raw Data'!H:H) -> 72946.52 | C13: =SUMIF('Raw Data'!K:K,A13,'Raw Data'!J:J) -> 28436.4
A14: Aug-25 | B14: =SUMIF('Raw Data'!K:K,A14,'Raw Data'!H:H) -> 93997.62 | C14: =SUMIF('Raw Data'!K:K,A14,'Raw Data'!J:J) -> 36540.98
A15: Sep-25 | B15: =SUMIF('Raw Data'!K:K,A15,'Raw Data'!H:H) -> 79360.66 | C15: =SUMIF('Raw Data'!K:K,A15,'Raw Data'!J:J) -> 30909.76
